codex/Coleccion_Cubos.py
codex/Inicio_de_sesion.py
codex/Seleccion_Cubos.py
codex/__init__.py
codex/res/__init__.py
Rubik_Vault-5.5.dist-info/LICENSE
Rubik_Vault-5.5.dist-info/METADATA
Rubik_Vault-5.5.dist-info/WHEEL
Rubik_Vault-5.5.dist-info/top_level.txt
Rubik_Vault-5.5.dist-info/RECORD
