Metadata-Version: 2.1
Name: Rubik_Vault
Version: 5.5
Summary: ¡Bienvenido a Rubik Vault, tu lugar para explorar y coleccionar imágenes de cubos Rubik!
Home-page: https://github.com/Michael-Esquivel/Rubik-Vault
Author: Michael Esquivel
Author-email: michaelesquivel100@gmail.com
Classifier: Environment :: Console
Classifier: Intended Audience :: Developers
Classifier: License :: OSI Approved :: MIT License
Classifier: Operating System :: OS Independent
Classifier: Programming Language :: Python
Classifier: Programming Language :: Python :: 3.9
Classifier: Programming Language :: Python :: 3.10
Classifier: Topic :: Utilities
License-File: LICENSE
